<?xml version="1.0" encoding="utf-8"?>
<!DOCTYPE hibernate-mapping PUBLIC "-//Hibernate/Hibernate Mapping DTD 3.0//EN"
"http://www.hibernate.org/dtd/hibernate-mapping-3.0.dtd">
<!-- 
    Mapping file autogenerated by MyEclipse Persistence Tools
-->
<hibernate-mapping>
    <class name="com.wy.entity.Audit" table="Audit" catalog="MicroFragment">
        <id name="eno" type="java.lang.Integer">
            <column name="Eno" />
            <generator class="native" />
        </id>
        <property name="adate" type="java.lang.String">
            <column name="Adate" length="45" not-null="true" />
        </property>
        <property name="astate" type="java.lang.String">
            <column name="Astate" length="45" not-null="true" />
        </property>
    </class>
</hibernate-mapping>
